{
  "schemaVersion": 1,
  "id": "dmntech",
  "version": "${version}",

  "name": "DmNTech",
  "description": "Remake IC2 for fabric!",
  "authors": [
    "DomamaN202"
  ],
  "contact": {
    "homepage": "https://github.com/Domaman202/DmNTech",
    "sources": "https://github.com/Domaman202/DmNTech"
  },

  "license": "CC0-1.0",
  "icon": "assets/dmntech/icon.png",

  "environment": "*",

  "entrypoints": {
    "main": [
      "ru.DmN.core.common.DCore",
      "ru.DmN.core.test.TestMain",
      "ru.DmN.tech.common.DTech",
      "ru.DmN.tech.test.TestMain"
    ],
    "client": [
      "ru.DmN.core.client.DCoreClient",
      "ru.DmN.tech.client.DTechClient",
      "ru.DmN.tech.test.TestClientMain"
    ]
  },

  "mixins": [
    "dmncore.mixins.json",
    "dmntech.mixins.json"
  ],

  "depends": {
    "fabricloader": "*",
    "fabric": "*",
    "minecraft": "*",
    "java": ">=16"
  },
  "suggests": {
    "another-mod": "*"
  }
}
